pydantic_argparse_extensible/__init__.py
pydantic_argparse_extensible/py.typed
pydantic_argparse_extensible-1.3.6.dist-info/METADATA
pydantic_argparse_extensible-1.3.6.dist-info/WHEEL
pydantic_argparse_extensible-1.3.6.dist-info/RECORD
