Metadata-Version: 2.1
Name: pydantic-argparse-extensible
Version: 1.3.6
Summary: A typed wrapper around argparse using pydantic models
License: MIT
Author: Rebecca Turner
Author-email: rbt@sent.as
Requires-Python: >=3.11,<4
Classifier: License :: OSI Approved :: MIT License
Classifier: Programming Language :: Python :: 3
Classifier: Programming Language :: Python :: 3.11
Classifier: Programming Language :: Python :: 3.12
Requires-Dist: pydantic (>=2.6.1,<3.0.0)
